BroachRpc/BroachApply.py
BroachRpc/BroachFramework.py
BroachRpc/__init__.py
BroachRpc/common/CommonDef.py
BroachRpc/common/GlobalVariable.py
BroachRpc/common/__init__.py
BroachRpc/exception/DefException.py
BroachRpc/exception/__init__.py
BroachRpc/network/MsgHandler.py
BroachRpc/network/RpcClient.py
BroachRpc/network/RpcServer.py
BroachRpc/network/RpcService.py
BroachRpc/network/__init__.py
BroachRpc/threadPool/AsyncPool.py
BroachRpc/threadPool/BroachPool.py
BroachRpc/threadPool/ThreadPool.py
BroachRpc/threadPool/__init__.py
BroachRpc-1.2.1.dist-info/LICENSE.txt
BroachRpc-1.2.1.dist-info/METADATA
BroachRpc-1.2.1.dist-info/WHEEL
BroachRpc-1.2.1.dist-info/top_level.txt
BroachRpc-1.2.1.dist-info/RECORD
