Metadata-Version: 2.1
Name: BroachRpc
Version: 1.2.1
Summary: 基于python的一个rpc微服务框架，开箱即用，无需注册中心
Home-page: https://github.com/KcangYan/BroachRpc
Author: kcangYan
Author-email: 842762472@qq.com
Maintainer: kcangYan
Maintainer-email: 842762472@qq.com
License: BSD License
Platform: all
Classifier: Development Status :: 4 - Beta
Classifier: Operating System :: OS Independent
Classifier: Intended Audience :: Developers
Classifier: License :: OSI Approved :: BSD License
Classifier: Programming Language :: Python
Classifier: Programming Language :: Python :: Implementation
Classifier: Programming Language :: Python :: 2
Classifier: Programming Language :: Python :: 2.7
Classifier: Programming Language :: Python :: 3
Classifier: Programming Language :: Python :: 3.4
Classifier: Programming Language :: Python :: 3.5
Classifier: Programming Language :: Python :: 3.6
Classifier: Topic :: Software Development :: Libraries
